facex/__init__.py
facex/component.py
facex/dataset.py
facex/face_model_v3.json
facex/farl.py
facex/hat_glasses.json
facex/nn_utils.py
facex/plot_facex.py
facex/run.py
facextool-0.1.52.dist-info/licenses/LICENSE
facextool-0.1.52.dist-info/METADATA
facextool-0.1.52.dist-info/WHEEL
facextool-0.1.52.dist-info/top_level.txt
facextool-0.1.52.dist-info/RECORD
