Metadata-Version: 2.4
Name: facextool
Version: 0.1.52
Summary: An XAI fairness assessment framework for face attribute classifiers
Home-page: https://github.com/gsarridis/faceX
Author: Ioannis Sarridis
Author-email: gsarridis@iti.gr
Classifier: Programming Language :: Python :: 3
Classifier: License :: OSI Approved :: Apache Software License
Classifier: Operating System :: OS Independent
Requires-Python: >=3.6
License-File: LICENSE
Requires-Dist: numpy>=2
Requires-Dist: opencv_python
Requires-Dist: Pillow
Requires-Dist: pyfacer
Requires-Dist: matplotlib>=3.10.3
Requires-Dist: torch
Requires-Dist: torchvision
Requires-Dist: tqdm
Requires-Dist: pandas
Requires-Dist: grad_cam==1.4.8
Requires-Dist: timm
Dynamic: author
Dynamic: author-email
Dynamic: classifier
Dynamic: description
Dynamic: description-content-type
Dynamic: home-page
Dynamic: license-file
Dynamic: requires-dist
Dynamic: requires-python
Dynamic: summary
